<annotation verified="yes">
	<folder>train</folder>
	<filename>iphone4_train_154.jpg</filename>
	<path>G:\Test3\models\research\object_detection\images\train\iphone4_train_154.jpg</path>
	<source>
		<database>Unknown</database>
	</source>
	<size>
		<width>177</width>
		<height>285</height>
		<depth>3</depth>
	</size>
	<segmented>0</segmented>
	<object>
		<name>iphone</name>
		<pose>Unspecified</pose>
		<truncated>0</truncated>
		<difficult>0</difficult>
		<bndbox>
			<xmin>87</xmin>
			<ymin>57</ymin>
			<xmax>161</xmax>
			<ymax>227</ymax>
		</bndbox>
	</object>
</annotation>
