<annotation>
	<folder>default</folder>
	<filename>face113.jpg</filename>
	<path>C:\Users\MSI\Desktop\face_detection\train\images\default\face113.jpg</path>
	<source>
		<database>Unknown</database>
	</source>
	<size>
		<width>431</width>
		<height>665</height>
		<depth>3</depth>
	</size>
	<segmented>0</segmented>
	<object>
		<name>face</name>
		<pose>Unspecified</pose>
		<truncated>0</truncated>
		<difficult>0</difficult>
		<bndbox>
			<xmin>151</xmin>
			<ymin>194</ymin>
			<xmax>211</xmax>
			<ymax>265</ymax>
		</bndbox>
	</object>
</annotation>
